{
    "spheres": [
        {
            "rightImg": "WestSide-Grass_100X_02_Right.JPG", 
            "markers": [
                {
                    "room": "Lobby_100", 
                    "number": "0", 
                    "radius": "0", 
                    "y": "0", 
                    "x": "0", 
                    "type": "walk"
                }
            ], 
            "leftImg": "WestSide-Grass_100X_02_Left.JPG"
        }, 
        {
            "rightImg": "WestSide-Grass_100X_03_Right.JPG", 
            "markers": [
                {
                    "room": "Lobby_100", 
                    "number": "0", 
                    "radius": "0", 
                    "y": "0", 
                    "x": "0", 
                    "type": "walk"
                }
            ], 
            "leftImg": "WestSide-Grass_100X_03_Left.JPG"
        }, 
        {
            "rightImg": "WestSide-Grass_100X_01_Right.JPG", 
            "markers": [
                {
                    "room": "Lobby_100", 
                    "number": "0", 
                    "radius": "0", 
                    "y": "0", 
                    "x": "0", 
                    "type": "walk"
                }
            ], 
            "leftImg": "WestSide-Grass_100X_01_Left.JPG"
        }, 
        {
            "rightImg": "WestSide-Grass_100X_04_Right.JPG", 
            "markers": [
                {
                    "room": "Lobby_100", 
                    "number": "0", 
                    "radius": "0", 
                    "y": "0", 
                    "x": "0", 
                    "type": "walk"
                }
            ], 
            "leftImg": "WestSide-Grass_100X_04_Left.JPG"
        }, 
        {
            "rightImg": "WestSide-Grass_100X_05_Right.JPG", 
            "markers": [
                {
                    "room": "Lobby_100", 
                    "number": "0", 
                    "radius": "0", 
                    "y": "0", 
                    "x": "0", 
                    "type": "walk"
                }
            ], 
            "leftImg": "WestSide-Grass_100X_05_Left.JPG"
        }
    ]
}